multicollinearity/__init__.py
multicollinearity/feature_reduction.py
multicollinearity/main.py
multi_collinearity-0.0.2.dist-info/LICENSE
multi_collinearity-0.0.2.dist-info/METADATA
multi_collinearity-0.0.2.dist-info/WHEEL
multi_collinearity-0.0.2.dist-info/top_level.txt
multi_collinearity-0.0.2.dist-info/RECORD
