Metadata-Version: 2.1
Name: multi-collinearity
Version: 0.0.2
Summary: Feature reduction using multi-collinearity
Author-email: Vishal Patel <vishal@derive.io>
Classifier: Programming Language :: Python :: 3
Classifier: License :: OSI Approved :: MIT License
Classifier: Operating System :: OS Independent
Requires-Python: >=3.7
License-File: LICENSE
